package/__init__.py
package/core.py
package/model_train.py
package/utils.py
atem_core-1.2.2.dist-info/METADATA
atem_core-1.2.2.dist-info/WHEEL
atem_core-1.2.2.dist-info/entry_points.txt
atem_core-1.2.2.dist-info/top_level.txt
atem_core-1.2.2.dist-info/RECORD
