Metadata-Version: 2.1
Name: atem_core
Version: 1.2.2
Summary: A Python package for adaptive task execution and machine learning integration.
Home-page: https://github.com/CapitalRobotics/ATEM.git
Author: Torin Etheridge
Author-email: torinriley220@gmail.com
Classifier: Programming Language :: Python :: 3
Classifier: License :: OSI Approved :: MIT License
Classifier: Operating System :: OS Independent
Requires-Python: >=3.7
Requires-Dist: tensorflow>=2.0.0
Requires-Dist: numpy>=1.18.0
